cizohosubscriptions/__init__.py
cizohosubscriptions/addon.py
cizohosubscriptions/customer.py
cizohosubscriptions/hostedpage.py
cizohosubscriptions/invoice.py
cizohosubscriptions/plan.py
cizohosubscriptions/subscription.py
cizohosubscriptions/token.py
client/__init__.py
client/client.py
subscriptions/__init__.py
subscriptions/addon.py
subscriptions/customer.py
subscriptions/hostedpage.py
subscriptions/invoice.py
subscriptions/plan.py
subscriptions/subscription.py
utils/__init__.py
utils/constants.py
cizohosubscriptions-1.0.2.dist-info/METADATA
cizohosubscriptions-1.0.2.dist-info/WHEEL
cizohosubscriptions-1.0.2.dist-info/top_level.txt
cizohosubscriptions-1.0.2.dist-info/RECORD
